{
  "image_id": "2043",
  "entities": {
    "T0": {
      "id": "T0",
      "type": "text",
      "bbox": [
        [
          57,
          19
        ],
        [
          564,
          64
        ]
      ],
      "value": "Recycling and the role of decomposers",
      "replacementText": "L",
      "category": "label"
    },
    "T1": {
      "id": "T1",
      "type": "text",
      "bbox": [
        [
          605,
          3
        ],
        [
          637,
          29
        ]
      ],
      "value": "14",
      "replacementText": "A",
      "category": "label"
    },
    "T10": {
      "id": "T10",
      "type": "text",
      "bbox": [
        [
          110,
          354
        ],
        [
          154,
          390
        ]
      ],
      "value": "die",
      "replacementText": "J",
      "category": "label"
    },
    "T11": {
      "id": "T11",
      "type": "text",
      "bbox": [
        [
          237,
          361
        ],
        [
          381,
          423
        ]
      ],
      "value": "Consumers animals",
      "replacementText": "G",
      "category": "label"
    },
    "T2": {
      "id": "T2",
      "type": "text",
      "bbox": [
        [
          523,
          108
        ],
        [
          607,
          134
        ]
      ],
      "value": "Sunlight",
      "replacementText": "B",
      "category": "label"
    },
    "T3": {
      "id": "T3",
      "type": "text",
      "bbox": [
        [
          393,
          76
        ],
        [
          513,
          160
        ]
      ],
      "value": "water and salts",
      "replacementText": "D",
      "category": "label"
    },
    "T4": {
      "id": "T4",
      "type": "text",
      "bbox": [
        [
          451,
          219
        ],
        [
          598,
          279
        ]
      ],
      "value": "PRODUCERS green plants",
      "replacementText": "H",
      "category": "label"
    },
    "T5": {
      "id": "T5",
      "type": "text",
      "bbox": [
        [
          456,
          343
        ],
        [
          514,
          383
        ]
      ],
      "value": "eaten",
      "replacementText": "I",
      "category": "label"
    },
    "T6": {
      "id": "T6",
      "type": "text",
      "bbox": [
        [
          300,
          229
        ],
        [
          330,
          245
        ]
      ],
      "value": "die",
      "replacementText": "K",
      "category": "label"
    },
    "T7": {
      "id": "T7",
      "type": "text",
      "bbox": [
        [
          229,
          82
        ],
        [
          362,
          157
        ]
      ],
      "value": "SOIL minerals and humus",
      "replacementText": "E",
      "category": "label"
    },
    "T8": {
      "id": "T8",
      "type": "text",
      "bbox": [
        [
          101,
          95
        ],
        [
          164,
          133
        ]
      ],
      "value": "decay",
      "replacementText": "C",
      "category": "label"
    },
    "T9": {
      "id": "T9",
      "type": "text",
      "bbox": [
        [
          40,
          226
        ],
        [
          217,
          276
        ]
      ],
      "value": "Decomposers bacteria and fungi",
      "replacementText": "F",
      "category": "label"
    },
    "A0": {
      "id": "A0",
      "type": "arrow",
      "polygon": [
        [
          71,
          209
        ],
        [
          83,
          188
        ],
        [
          99,
          161
        ],
        [
          125,
          135
        ],
        [
          159,
          115
        ],
        [
          199,
          102
        ],
        [
          221,
          99
        ],
        [
          219,
          86
        ],
        [
          243,
          98
        ],
        [
          230,
          117
        ],
        [
          227,
          111
        ],
        [
          213,
          112
        ],
        [
          188,
          117
        ],
        [
          159,
          129
        ],
        [
          139,
          141
        ],
        [
          119,
          155
        ],
        [
          100,
          177
        ],
        [
          91,
          193
        ],
        [
          85,
          216
        ],
        [
          70,
          210
        ]
      ],
      "category": "connector"
    },
    "A1": {
      "id": "A1",
      "type": "arrow",
      "polygon": [
        [
          213,
          376
        ],
        [
          187,
          369
        ],
        [
          169,
          361
        ],
        [
          144,
          346
        ],
        [
          127,
          333
        ],
        [
          110,
          317
        ],
        [
          104,
          305
        ],
        [
          110,
          301
        ],
        [
          87,
          288
        ],
        [
          85,
          309
        ],
        [
          94,
          309
        ],
        [
          100,
          320
        ],
        [
          116,
          338
        ],
        [
          137,
          355
        ],
        [
          162,
          369
        ],
        [
          197,
          384
        ],
        [
          216,
          388
        ],
        [
          215,
          375
        ]
      ],
      "category": "connector"
    },
    "A2": {
      "id": "A2",
      "type": "arrow",
      "polygon": [
        [
          400,
          244
        ],
        [
          262,
          246
        ],
        [
          259,
          239
        ],
        [
          242,
          248
        ],
        [
          256,
          261
        ],
        [
          258,
          255
        ],
        [
          405,
          257
        ],
        [
          401,
          246
        ]
      ],
      "category": "connector"
    },
    "A3": {
      "id": "A3",
      "type": "arrow",
      "polygon": [
        [
          356,
          94
        ],
        [
          381,
          101
        ],
        [
          411,
          108
        ],
        [
          435,
          117
        ],
        [
          457,
          130
        ],
        [
          478,
          148
        ],
        [
          498,
          169
        ],
        [
          510,
          196
        ],
        [
          519,
          194
        ],
        [
          512,
          214
        ],
        [
          491,
          202
        ],
        [
          499,
          199
        ],
        [
          495,
          184
        ],
        [
          479,
          162
        ],
        [
          459,
          143
        ],
        [
          436,
          129
        ],
        [
          411,
          119
        ],
        [
          380,
          111
        ],
        [
          353,
          109
        ],
        [
          356,
          96
        ]
      ],
      "category": "connector"
    },
    "A4": {
      "id": "A4",
      "type": "arrow",
      "polygon": [
        [
          563,
          141
        ],
        [
          571,
          141
        ],
        [
          572,
          196
        ],
        [
          579,
          198
        ],
        [
          567,
          213
        ],
        [
          555,
          197
        ],
        [
          563,
          197
        ],
        [
          563,
          142
        ]
      ],
      "category": "connector"
    },
    "A5": {
      "id": "A5",
      "type": "arrow",
      "polygon": [
        [
          509,
          289
        ],
        [
          522,
          293
        ],
        [
          517,
          305
        ],
        [
          505,
          324
        ],
        [
          494,
          337
        ],
        [
          477,
          353
        ],
        [
          462,
          363
        ],
        [
          442,
          371
        ],
        [
          417,
          381
        ],
        [
          419,
          389
        ],
        [
          393,
          384
        ],
        [
          409,
          361
        ],
        [
          412,
          370
        ],
        [
          430,
          365
        ],
        [
          456,
          353
        ],
        [
          476,
          339
        ],
        [
          494,
          320
        ],
        [
          503,
          309
        ],
        [
          510,
          290
        ]
      ],
      "category": "connector"
    }
  },
  "relationships": [
    {
      "id": "A0+H4",
      "type": "arrowHeadTail",
      "source": "A0",
      "target": "H4",
      "connector": null,
      "directional": false
    },
    {
      "id": "A1+H3",
      "type": "arrowHeadTail",
      "source": "A1",
      "target": "H3",
      "connector": null,
      "directional": false
    },
    {
      "id": "A2+H1",
      "type": "arrowHeadTail",
      "source": "A2",
      "target": "H1",
      "connector": null,
      "directional": false
    },
    {
      "id": "A3+H2",
      "type": "arrowHeadTail",
      "source": "A3",
      "target": "H2",
      "connector": null,
      "directional": false
    },
    {
      "id": "A4+H5",
      "type": "arrowHeadTail",
      "source": "A4",
      "target": "H5",
      "connector": null,
      "directional": false
    },
    {
      "id": "A5+H0",
      "type": "arrowHeadTail",
      "source": "A5",
      "target": "H0",
      "connector": null,
      "directional": false
    },
    {
      "id": "T11+A1+T9",
      "type": "interObjectLinkage",
      "source": "T11",
      "target": "T9",
      "connector": "A1",
      "directional": true
    },
    {
      "id": "T2+A4+T4",
      "type": "interObjectLinkage",
      "source": "T2",
      "target": "T4",
      "connector": "A4",
      "directional": true
    },
    {
      "id": "T4+A2+T9",
      "type": "interObjectLinkage",
      "source": "T4",
      "target": "T9",
      "connector": "A2",
      "directional": true
    },
    {
      "id": "T4+A5+T11",
      "type": "interObjectLinkage",
      "source": "T4",
      "target": "T11",
      "connector": "A5",
      "directional": true
    },
    {
      "id": "T7+A3+T4",
      "type": "interObjectLinkage",
      "source": "T7",
      "target": "T4",
      "connector": "A3",
      "directional": true
    },
    {
      "id": "T9+A0+T7",
      "type": "interObjectLinkage",
      "source": "T9",
      "target": "T7",
      "connector": "A0",
      "directional": true
    }
  ],
  "semantic_roles": {
    "T0": "part_label",
    "T1": "part_label",
    "T10": "part_label",
    "T11": "part_label",
    "T2": "part_label",
    "T3": "part_label",
    "T4": "part_label",
    "T5": "part_label",
    "T6": "part_label",
    "T7": "part_label",
    "T8": "part_label",
    "T9": "part_label",
    "A0": "connector",
    "A1": "connector",
    "A2": "connector",
    "A3": "connector",
    "A4": "connector",
    "A5": "connector"
  },
  "educational_context": {
    "subject": "biology",
    "diagram_type": "flow_diagram",
    "text_content": "recycling and the role of decomposers 14 die consumers animals sunlight water and salts producers green plants eaten die soil minerals and humus decay decomposers bacteria and fungi"
  }
}