{
  "image_id": "3141",
  "entities": {
    "T0": {
      "id": "T0",
      "type": "text",
      "bbox": [
        [
          381,
          41
        ],
        [
          493,
          75
        ]
      ],
      "value": "Cuticle",
      "replacementText": "E",
      "category": "label"
    },
    "T1": {
      "id": "T1",
      "type": "text",
      "bbox": [
        [
          388,
          92
        ],
        [
          534,
          126
        ]
      ],
      "value": "Epidermis",
      "replacementText": "B",
      "category": "label"
    },
    "T2": {
      "id": "T2",
      "type": "text",
      "bbox": [
        [
          386,
          145
        ],
        [
          536,
          204
        ]
      ],
      "value": "Palisade mesophyll",
      "replacementText": "H",
      "category": "label"
    },
    "T3": {
      "id": "T3",
      "type": "text",
      "bbox": [
        [
          388,
          227
        ],
        [
          526,
          255
        ]
      ],
      "value": "Air Space",
      "replacementText": "G",
      "category": "label"
    },
    "T4": {
      "id": "T4",
      "type": "text",
      "bbox": [
        [
          349,
          271
        ],
        [
          423,
          306
        ]
      ],
      "value": "Vein",
      "replacementText": "I",
      "category": "label"
    },
    "T5": {
      "id": "T5",
      "type": "text",
      "bbox": [
        [
          304,
          318
        ],
        [
          445,
          352
        ]
      ],
      "value": "Stomata",
      "replacementText": "J",
      "category": "label"
    },
    "T6": {
      "id": "T6",
      "type": "text",
      "bbox": [
        [
          263,
          369
        ],
        [
          418,
          425
        ]
      ],
      "value": "Spongy mesophyll",
      "replacementText": "A",
      "category": "label"
    },
    "T7": {
      "id": "T7",
      "type": "text",
      "bbox": [
        [
          96,
          393
        ],
        [
          159,
          432
        ]
      ],
      "value": "H2O",
      "replacementText": "D",
      "category": "label"
    },
    "T8": {
      "id": "T8",
      "type": "text",
      "bbox": [
        [
          173,
          397
        ],
        [
          219,
          429
        ]
      ],
      "value": "O2",
      "replacementText": "C",
      "category": "label"
    },
    "T9": {
      "id": "T9",
      "type": "text",
      "bbox": [
        [
          163,
          328
        ],
        [
          226,
          366
        ]
      ],
      "value": "CO2",
      "replacementText": "F",
      "category": "label"
    },
    "B0": {
      "id": "B0",
      "type": "blob",
      "polygon": [
        [
          370,
          226
        ],
        [
          318,
          298
        ],
        [
          299,
          320
        ],
        [
          280,
          343
        ],
        [
          259,
          362
        ],
        [
          253,
          366
        ],
        [
          236,
          372
        ],
        [
          205,
          376
        ],
        [
          177,
          381
        ],
        [
          149,
          384
        ],
        [
          119,
          385
        ],
        [
          85,
          386
        ],
        [
          58,
          382
        ],
        [
          19,
          377
        ],
        [
          0,
          393
        ],
        [
          0,
          359
        ],
        [
          0,
          328
        ],
        [
          0,
          141
        ],
        [
          26,
          119
        ],
        [
          69,
          98
        ],
        [
          103,
          84
        ],
        [
          146,
          69
        ],
        [
          193,
          51
        ],
        [
          233,
          40
        ],
        [
          276,
          31
        ],
        [
          313,
          30
        ],
        [
          315,
          47
        ],
        [
          322,
          73
        ],
        [
          325,
          87
        ],
        [
          333,
          101
        ],
        [
          335,
          117
        ],
        [
          338,
          127
        ],
        [
          341,
          134
        ],
        [
          342,
          143
        ],
        [
          342,
          158
        ],
        [
          340,
          163
        ],
        [
          336,
          169
        ],
        [
          340,
          176
        ],
        [
          354,
          176
        ],
        [
          358,
          185
        ],
        [
          362,
          197
        ],
        [
          364,
          203
        ],
        [
          366,
          203
        ],
        [
          370,
          222
        ]
      ],
      "category": "object"
    },
    "A0": {
      "id": "A0",
      "type": "arrow",
      "polygon": [
        [
          298,
          35
        ],
        [
          298,
          49
        ],
        [
          384,
          70
        ],
        [
          388,
          53
        ],
        [
          299,
          34
        ]
      ],
      "category": "connector"
    },
    "A1": {
      "id": "A1",
      "type": "arrow",
      "polygon": [
        [
          296,
          50
        ],
        [
          292,
          64
        ],
        [
          384,
          112
        ],
        [
          390,
          95
        ],
        [
          299,
          53
        ]
      ],
      "category": "connector"
    },
    "A10": {
      "id": "A10",
      "type": "arrow",
      "polygon": [
        [
          141,
          302
        ],
        [
          116,
          400
        ],
        [
          133,
          401
        ],
        [
          163,
          303
        ],
        [
          143,
          303
        ]
      ],
      "category": "connector"
    },
    "A2": {
      "id": "A2",
      "type": "arrow",
      "polygon": [
        [
          292,
          75
        ],
        [
          284,
          89
        ],
        [
          388,
          150
        ],
        [
          400,
          139
        ],
        [
          294,
          75
        ]
      ],
      "category": "connector"
    },
    "A3": {
      "id": "A3",
      "type": "arrow",
      "polygon": [
        [
          311,
          109
        ],
        [
          315,
          132
        ],
        [
          396,
          157
        ],
        [
          397,
          136
        ],
        [
          311,
          107
        ]
      ],
      "category": "connector"
    },
    "A4": {
      "id": "A4",
      "type": "arrow",
      "polygon": [
        [
          299,
          171
        ],
        [
          303,
          198
        ],
        [
          389,
          235
        ],
        [
          402,
          217
        ],
        [
          300,
          171
        ]
      ],
      "category": "connector"
    },
    "A5": {
      "id": "A5",
      "type": "arrow",
      "polygon": [
        [
          192,
          105
        ],
        [
          194,
          121
        ],
        [
          214,
          120
        ],
        [
          240,
          198
        ],
        [
          351,
          284
        ],
        [
          359,
          267
        ],
        [
          260,
          187
        ],
        [
          229,
          102
        ],
        [
          195,
          104
        ]
      ],
      "category": "connector"
    },
    "A6": {
      "id": "A6",
      "type": "arrow",
      "polygon": [
        [
          254,
          290
        ],
        [
          248,
          304
        ],
        [
          311,
          345
        ],
        [
          323,
          331
        ],
        [
          257,
          288
        ]
      ],
      "category": "connector"
    },
    "A7": {
      "id": "A7",
      "type": "arrow",
      "polygon": [
        [
          167,
          238
        ],
        [
          180,
          231
        ],
        [
          298,
          363
        ],
        [
          291,
          372
        ],
        [
          166,
          240
        ]
      ],
      "category": "connector"
    },
    "A8": {
      "id": "A8",
      "type": "arrow",
      "polygon": [
        [
          113,
          247
        ],
        [
          103,
          261
        ],
        [
          287,
          374
        ],
        [
          300,
          355
        ],
        [
          115,
          249
        ]
      ],
      "category": "connector"
    },
    "A9": {
      "id": "A9",
      "type": "arrow",
      "polygon": [
        [
          140,
          314
        ],
        [
          167,
          400
        ],
        [
          184,
          396
        ],
        [
          155,
          310
        ],
        [
          137,
          312
        ]
      ],
      "category": "connector"
    }
  },
  "relationships": [
    {
      "id": "A10+H0",
      "type": "arrowHeadTail",
      "source": "A10",
      "target": "H0",
      "connector": null,
      "directional": false
    },
    {
      "id": "A9+H1",
      "type": "arrowHeadTail",
      "source": "A9",
      "target": "H1",
      "connector": null,
      "directional": false
    },
    {
      "id": "T0+A0+B0",
      "type": "intraObjectLinkage",
      "source": "T0",
      "target": "B0",
      "connector": "A0",
      "directional": false
    },
    {
      "id": "T1+A1+B0",
      "type": "intraObjectLinkage",
      "source": "T1",
      "target": "B0",
      "connector": "A1",
      "directional": false
    },
    {
      "id": "T2+A2+B0",
      "type": "intraObjectLinkage",
      "source": "T2",
      "target": "B0",
      "connector": "A2",
      "directional": false
    },
    {
      "id": "T2+A3+B0",
      "type": "intraObjectLinkage",
      "source": "T2",
      "target": "B0",
      "connector": "A3",
      "directional": false
    },
    {
      "id": "T3+A4+B0",
      "type": "intraObjectLinkage",
      "source": "T3",
      "target": "B0",
      "connector": "A4",
      "directional": false
    },
    {
      "id": "T4+A5+B0",
      "type": "intraObjectLinkage",
      "source": "T4",
      "target": "B0",
      "connector": "A5",
      "directional": false
    },
    {
      "id": "T5+A6+B0",
      "type": "intraObjectLinkage",
      "source": "T5",
      "target": "B0",
      "connector": "A6",
      "directional": false
    },
    {
      "id": "T6+A7+B0",
      "type": "intraObjectLinkage",
      "source": "T6",
      "target": "B0",
      "connector": "A7",
      "directional": false
    },
    {
      "id": "T6+A8+B0",
      "type": "intraObjectLinkage",
      "source": "T6",
      "target": "B0",
      "connector": "A8",
      "directional": false
    },
    {
      "id": "T7+A10+B0",
      "type": "intraObjectLinkage",
      "source": "T7",
      "target": "B0",
      "connector": "A10",
      "directional": false
    },
    {
      "id": "T8+A9+B0",
      "type": "intraObjectLinkage",
      "source": "T8",
      "target": "B0",
      "connector": "A9",
      "directional": false
    },
    {
      "id": "T9+B0",
      "type": "intraObjectRegionLabel",
      "source": "T9",
      "target": "B0",
      "connector": null,
      "directional": false
    }
  ],
  "semantic_roles": {
    "T0": "part_label",
    "T1": "part_label",
    "T2": "part_label",
    "T3": "part_label",
    "T4": "part_label",
    "T5": "part_label",
    "T6": "part_label",
    "T7": "part_label",
    "T8": "part_label",
    "T9": "part_label",
    "B0": "whole",
    "A0": "connector",
    "A1": "connector",
    "A10": "connector",
    "A2": "connector",
    "A3": "connector",
    "A4": "connector",
    "A5": "connector",
    "A6": "connector",
    "A7": "connector",
    "A8": "connector",
    "A9": "connector"
  },
  "educational_context": {
    "subject": "unknown",
    "diagram_type": "flow_diagram",
    "text_content": "cuticle epidermis palisade mesophyll air space vein stomata spongy mesophyll h2o o2 co2"
  },
  "questions": [
    {
      "question_text": "What is the layer below the cuticle?",
      "question_id": "3141.png-0",
      "answers": [
        "Air space",
        "Epidermis",
        "Vein",
        "Stomata"
      ],
      "correct_answer_index": 1,
      "abc_label": false
    },
    {
      "question_text": "Which section covers the epidermis?",
      "question_id": "3141.png-1",
      "answers": [
        "Cuticle",
        "Stomata",
        "Air Space",
        "Vein"
      ],
      "correct_answer_index": 0,
      "abc_label": true
    }
  ]
}