{
  "image_id": "4709",
  "entities": {
    "T0": {
      "id": "T0",
      "type": "text",
      "bbox": [
        [
          2,
          152
        ],
        [
          75,
          169
        ]
      ],
      "value": "attenuate",
      "replacementText": "E",
      "category": "label"
    },
    "T1": {
      "id": "T1",
      "type": "text",
      "bbox": [
        [
          100,
          105
        ],
        [
          164,
          120
        ]
      ],
      "value": "cuneate",
      "replacementText": "H",
      "category": "label"
    },
    "T10": {
      "id": "T10",
      "type": "text",
      "bbox": [
        [
          21,
          269
        ],
        [
          77,
          281
        ]
      ],
      "value": "cordate",
      "replacementText": "A",
      "category": "label"
    },
    "T2": {
      "id": "T2",
      "type": "text",
      "bbox": [
        [
          206,
          101
        ],
        [
          268,
          113
        ]
      ],
      "value": "rounded",
      "replacementText": "C",
      "category": "label"
    },
    "T3": {
      "id": "T3",
      "type": "text",
      "bbox": [
        [
          310,
          91
        ],
        [
          374,
          105
        ]
      ],
      "value": "truncate",
      "replacementText": "F",
      "category": "label"
    },
    "T4": {
      "id": "T4",
      "type": "text",
      "bbox": [
        [
          443,
          116
        ],
        [
          499,
          132
        ]
      ],
      "value": "oblique",
      "replacementText": "I",
      "category": "label"
    },
    "T5": {
      "id": "T5",
      "type": "text",
      "bbox": [
        [
          481,
          231
        ],
        [
          561,
          253
        ]
      ],
      "value": "sheathing",
      "replacementText": "J",
      "category": "label"
    },
    "T6": {
      "id": "T6",
      "type": "text",
      "bbox": [
        [
          390,
          262
        ],
        [
          440,
          279
        ]
      ],
      "value": "peltate",
      "replacementText": "D",
      "category": "label"
    },
    "T7": {
      "id": "T7",
      "type": "text",
      "bbox": [
        [
          287,
          211
        ],
        [
          342,
          223
        ]
      ],
      "value": "hastate",
      "replacementText": "G",
      "category": "label"
    },
    "T8": {
      "id": "T8",
      "type": "text",
      "bbox": [
        [
          214,
          259
        ],
        [
          282,
          276
        ]
      ],
      "value": "perfoliate",
      "replacementText": "B",
      "category": "label"
    },
    "T9": {
      "id": "T9",
      "type": "text",
      "bbox": [
        [
          126,
          241
        ],
        [
          191,
          258
        ]
      ],
      "value": "sagittate",
      "replacementText": "K",
      "category": "label"
    },
    "B0": {
      "id": "B0",
      "type": "blob",
      "polygon": [
        [
          7,
          45
        ],
        [
          25,
          114
        ],
        [
          28,
          129
        ],
        [
          20,
          147
        ],
        [
          45,
          137
        ],
        [
          38,
          128
        ],
        [
          44,
          87
        ],
        [
          56,
          35
        ],
        [
          49,
          14
        ],
        [
          38,
          14
        ],
        [
          31,
          9
        ],
        [
          18,
          13
        ],
        [
          21,
          26
        ],
        [
          9,
          41
        ]
      ],
      "category": "object"
    },
    "B1": {
      "id": "B1",
      "type": "blob",
      "polygon": [
        [
          80,
          53
        ],
        [
          89,
          41
        ],
        [
          98,
          39
        ],
        [
          114,
          40
        ],
        [
          114,
          40
        ],
        [
          114,
          40
        ],
        [
          127,
          38
        ],
        [
          126,
          30
        ],
        [
          132,
          25
        ],
        [
          140,
          32
        ],
        [
          145,
          28
        ],
        [
          157,
          35
        ],
        [
          167,
          47
        ],
        [
          177,
          39
        ],
        [
          183,
          45
        ],
        [
          135,
          103
        ],
        [
          125,
          104
        ],
        [
          78,
          58
        ],
        [
          78,
          58
        ],
        [
          79,
          56
        ]
      ],
      "category": "object"
    },
    "B10": {
      "id": "B10",
      "type": "blob",
      "polygon": [
        [
          95,
          227
        ],
        [
          64,
          251
        ],
        [
          54,
          240
        ],
        [
          48,
          262
        ],
        [
          42,
          243
        ],
        [
          20,
          239
        ],
        [
          12,
          221
        ],
        [
          19,
          189
        ],
        [
          67,
          181
        ],
        [
          95,
          219
        ],
        [
          95,
          219
        ],
        [
          97,
          228
        ]
      ],
      "category": "object"
    },
    "B2": {
      "id": "B2",
      "type": "blob",
      "polygon": [
        [
          204,
          19
        ],
        [
          278,
          22
        ],
        [
          271,
          48
        ],
        [
          256,
          72
        ],
        [
          243,
          80
        ],
        [
          240,
          98
        ],
        [
          231,
          98
        ],
        [
          230,
          83
        ],
        [
          219,
          71
        ],
        [
          210,
          57
        ],
        [
          203,
          38
        ],
        [
          202,
          19
        ]
      ],
      "category": "object"
    },
    "B3": {
      "id": "B3",
      "type": "blob",
      "polygon": [
        [
          319,
          20
        ],
        [
          305,
          54
        ],
        [
          305,
          54
        ],
        [
          316,
          73
        ],
        [
          342,
          72
        ],
        [
          344,
          90
        ],
        [
          348,
          72
        ],
        [
          373,
          73
        ],
        [
          389,
          56
        ],
        [
          382,
          20
        ],
        [
          374,
          16
        ],
        [
          348,
          42
        ],
        [
          320,
          21
        ]
      ],
      "category": "object"
    },
    "B4": {
      "id": "B4",
      "type": "blob",
      "polygon": [
        [
          422,
          19
        ],
        [
          432,
          78
        ],
        [
          466,
          103
        ],
        [
          473,
          99
        ],
        [
          471,
          111
        ],
        [
          479,
          108
        ],
        [
          481,
          92
        ],
        [
          506,
          65
        ],
        [
          521,
          23
        ],
        [
          490,
          28
        ],
        [
          427,
          19
        ],
        [
          423,
          19
        ]
      ],
      "category": "object"
    },
    "B5": {
      "id": "B5",
      "type": "blob",
      "polygon": [
        [
          534,
          16
        ],
        [
          526,
          51
        ],
        [
          530,
          85
        ],
        [
          526,
          111
        ],
        [
          530,
          155
        ],
        [
          525,
          168
        ],
        [
          503,
          198
        ],
        [
          489,
          223
        ],
        [
          491,
          230
        ],
        [
          499,
          230
        ],
        [
          541,
          167
        ],
        [
          547,
          167
        ],
        [
          552,
          155
        ],
        [
          564,
          124
        ],
        [
          555,
          128
        ],
        [
          554,
          85
        ],
        [
          550,
          58
        ],
        [
          538,
          15
        ]
      ],
      "category": "object"
    },
    "B6": {
      "id": "B6",
      "type": "blob",
      "polygon": [
        [
          421,
          169
        ],
        [
          447,
          177
        ],
        [
          464,
          201
        ],
        [
          470,
          221
        ],
        [
          447,
          237
        ],
        [
          426,
          235
        ],
        [
          427,
          254
        ],
        [
          423,
          267
        ],
        [
          419,
          263
        ],
        [
          417,
          246
        ],
        [
          416,
          233
        ],
        [
          404,
          233
        ],
        [
          385,
          230
        ],
        [
          381,
          220
        ],
        [
          373,
          207
        ],
        [
          379,
          193
        ],
        [
          401,
          175
        ],
        [
          420,
          169
        ]
      ],
      "category": "object"
    },
    "B7": {
      "id": "B7",
      "type": "blob",
      "polygon": [
        [
          295,
          120
        ],
        [
          338,
          122
        ],
        [
          340,
          140
        ],
        [
          356,
          140
        ],
        [
          381,
          149
        ],
        [
          400,
          162
        ],
        [
          383,
          177
        ],
        [
          358,
          176
        ],
        [
          332,
          169
        ],
        [
          325,
          163
        ],
        [
          318,
          169
        ],
        [
          320,
          204
        ],
        [
          311,
          205
        ],
        [
          311,
          167
        ],
        [
          304,
          168
        ],
        [
          289,
          174
        ],
        [
          272,
          170
        ],
        [
          248,
          162
        ],
        [
          237,
          154
        ],
        [
          258,
          147
        ],
        [
          282,
          140
        ],
        [
          290,
          132
        ],
        [
          296,
          119
        ]
      ],
      "category": "object"
    },
    "B8": {
      "id": "B8",
      "type": "blob",
      "polygon": [
        [
          244,
          181
        ],
        [
          283,
          231
        ],
        [
          273,
          242
        ],
        [
          247,
          245
        ],
        [
          247,
          256
        ],
        [
          240,
          256
        ],
        [
          240,
          245
        ],
        [
          220,
          239
        ],
        [
          216,
          222
        ],
        [
          225,
          204
        ],
        [
          223,
          188
        ],
        [
          227,
          185
        ],
        [
          231,
          196
        ],
        [
          242,
          181
        ]
      ],
      "category": "object"
    },
    "B9": {
      "id": "B9",
      "type": "blob",
      "polygon": [
        [
          110,
          179
        ],
        [
          122,
          153
        ],
        [
          156,
          176
        ],
        [
          157,
          175
        ],
        [
          158,
          141
        ],
        [
          166,
          140
        ],
        [
          167,
          171
        ],
        [
          187,
          147
        ],
        [
          205,
          162
        ],
        [
          202,
          203
        ],
        [
          189,
          225
        ],
        [
          168,
          219
        ],
        [
          168,
          231
        ],
        [
          157,
          233
        ],
        [
          157,
          223
        ],
        [
          140,
          226
        ],
        [
          124,
          218
        ],
        [
          108,
          179
        ]
      ],
      "category": "object"
    }
  },
  "relationships": [
    {
      "id": "T0+B0",
      "type": "intraObjectLabel",
      "source": "T0",
      "target": "B0",
      "connector": null,
      "directional": false
    },
    {
      "id": "T1+B1",
      "type": "intraObjectLabel",
      "source": "T1",
      "target": "B1",
      "connector": null,
      "directional": false
    },
    {
      "id": "T10+B10",
      "type": "intraObjectLabel",
      "source": "T10",
      "target": "B10",
      "connector": null,
      "directional": false
    },
    {
      "id": "T2+B2",
      "type": "intraObjectLabel",
      "source": "T2",
      "target": "B2",
      "connector": null,
      "directional": false
    },
    {
      "id": "T3+B3",
      "type": "intraObjectLabel",
      "source": "T3",
      "target": "B3",
      "connector": null,
      "directional": false
    },
    {
      "id": "T4+B4",
      "type": "intraObjectLabel",
      "source": "T4",
      "target": "B4",
      "connector": null,
      "directional": false
    },
    {
      "id": "T5+B5",
      "type": "intraObjectLabel",
      "source": "T5",
      "target": "B5",
      "connector": null,
      "directional": false
    },
    {
      "id": "T6+B6",
      "type": "intraObjectLabel",
      "source": "T6",
      "target": "B6",
      "connector": null,
      "directional": false
    },
    {
      "id": "T7+B7",
      "type": "intraObjectLabel",
      "source": "T7",
      "target": "B7",
      "connector": null,
      "directional": false
    },
    {
      "id": "T8+B8",
      "type": "intraObjectLabel",
      "source": "T8",
      "target": "B8",
      "connector": null,
      "directional": false
    },
    {
      "id": "T9+B9",
      "type": "intraObjectLabel",
      "source": "T9",
      "target": "B9",
      "connector": null,
      "directional": false
    }
  ],
  "semantic_roles": {
    "T0": "part_label",
    "T1": "part_label",
    "T10": "part_label",
    "T2": "part_label",
    "T3": "part_label",
    "T4": "part_label",
    "T5": "part_label",
    "T6": "part_label",
    "T7": "part_label",
    "T8": "part_label",
    "T9": "part_label",
    "B0": "whole",
    "B1": "whole",
    "B10": "whole",
    "B2": "whole",
    "B3": "whole",
    "B4": "whole",
    "B5": "whole",
    "B6": "whole",
    "B7": "whole",
    "B8": "whole",
    "B9": "whole"
  },
  "educational_context": {
    "subject": "unknown",
    "diagram_type": "labeled_illustration",
    "text_content": "attenuate cuneate cordate rounded truncate oblique sheathing peltate hastate perfoliate sagittate"
  },
  "questions": [
    {
      "question_text": "The diagram represents which part of a plant?",
      "question_id": "4709.png-0",
      "answers": [
        "Branches",
        "Trunks",
        "Leaves",
        "Flowers"
      ],
      "correct_answer_index": 2,
      "abc_label": true
    },
    {
      "question_text": "Which leaf is shaped like an arrowhead?",
      "question_id": "4709.png-2",
      "answers": [
        "oblique",
        "sagittate",
        "perfoliate",
        "attenuate"
      ],
      "correct_answer_index": 1,
      "abc_label": false
    },
    {
      "question_text": "Which of these show peltate type of leaf?",
      "question_id": "4709.png-1",
      "answers": [
        "A",
        "D",
        "G",
        "J"
      ],
      "correct_answer_index": 1,
      "abc_label": true
    }
  ]
}