{
  "image_id": "4733",
  "entities": {
    "T0": {
      "id": "T0",
      "type": "text",
      "bbox": [
        [
          75,
          205
        ],
        [
          230,
          242
        ]
      ],
      "value": "acuminate",
      "replacementText": "R",
      "category": "label"
    },
    "T1": {
      "id": "T1",
      "type": "text",
      "bbox": [
        [
          292,
          208
        ],
        [
          401,
          235
        ]
      ],
      "value": "straight",
      "replacementText": "B",
      "category": "label"
    },
    "T10": {
      "id": "T10",
      "type": "text",
      "bbox": [
        [
          708,
          850
        ],
        [
          819,
          873
        ]
      ],
      "value": "convex",
      "replacementText": "N",
      "category": "label"
    },
    "T11": {
      "id": "T11",
      "type": "text",
      "bbox": [
        [
          674,
          1054
        ],
        [
          819,
          1094
        ]
      ],
      "value": "landmark",
      "replacementText": "M",
      "category": "label"
    },
    "T12": {
      "id": "T12",
      "type": "text",
      "bbox": [
        [
          294,
          1075
        ],
        [
          397,
          1116
        ]
      ],
      "value": "lamina",
      "replacementText": "G",
      "category": "label"
    },
    "T13": {
      "id": "T13",
      "type": "text",
      "bbox": [
        [
          292,
          1190
        ],
        [
          397,
          1220
        ]
      ],
      "value": "petiole",
      "replacementText": "D",
      "category": "label"
    },
    "T14": {
      "id": "T14",
      "type": "text",
      "bbox": [
        [
          0,
          918
        ],
        [
          31,
          957
        ]
      ],
      "value": "D",
      "replacementText": "Q",
      "category": "label"
    },
    "T15": {
      "id": "T15",
      "type": "text",
      "bbox": [
        [
          4,
          676
        ],
        [
          34,
          711
        ]
      ],
      "value": "C",
      "replacementText": "H",
      "category": "label"
    },
    "T16": {
      "id": "T16",
      "type": "text",
      "bbox": [
        [
          1,
          294
        ],
        [
          26,
          333
        ]
      ],
      "value": "B",
      "replacementText": "F",
      "category": "label"
    },
    "T17": {
      "id": "T17",
      "type": "text",
      "bbox": [
        [
          0,
          0
        ],
        [
          31,
          28
        ]
      ],
      "value": "A",
      "replacementText": "P",
      "category": "label"
    },
    "T2": {
      "id": "T2",
      "type": "text",
      "bbox": [
        [
          484,
          203
        ],
        [
          626,
          233
        ]
      ],
      "value": "rounded",
      "replacementText": "I",
      "category": "label"
    },
    "T3": {
      "id": "T3",
      "type": "text",
      "bbox": [
        [
          742,
          208
        ],
        [
          919,
          242
        ]
      ],
      "value": "emarginate",
      "replacementText": "E",
      "category": "label"
    },
    "T4": {
      "id": "T4",
      "type": "text",
      "bbox": [
        [
          773,
          588
        ],
        [
          890,
          627
        ]
      ],
      "value": "oblong",
      "replacementText": "L",
      "category": "label"
    },
    "T5": {
      "id": "T5",
      "type": "text",
      "bbox": [
        [
          555,
          596
        ],
        [
          639,
          619
        ]
      ],
      "value": "ovate",
      "replacementText": "K",
      "category": "label"
    },
    "T6": {
      "id": "T6",
      "type": "text",
      "bbox": [
        [
          316,
          583
        ],
        [
          427,
          627
        ]
      ],
      "value": "elliptic",
      "replacementText": "O",
      "category": "label"
    },
    "T7": {
      "id": "T7",
      "type": "text",
      "bbox": [
        [
          80,
          596
        ],
        [
          210,
          622
        ]
      ],
      "value": "obovate",
      "replacementText": "C",
      "category": "label"
    },
    "T8": {
      "id": "T8",
      "type": "text",
      "bbox": [
        [
          87,
          849
        ],
        [
          213,
          879
        ]
      ],
      "value": "straight",
      "replacementText": "A",
      "category": "label"
    },
    "T9": {
      "id": "T9",
      "type": "text",
      "bbox": [
        [
          364,
          845
        ],
        [
          498,
          878
        ]
      ],
      "value": "rounded",
      "replacementText": "J",
      "category": "label"
    },
    "B0": {
      "id": "B0",
      "type": "blob",
      "polygon": [
        [
          255,
          183
        ],
        [
          169,
          85
        ],
        [
          155,
          0
        ],
        [
          138,
          3
        ],
        [
          128,
          73
        ],
        [
          90,
          115
        ],
        [
          53,
          198
        ],
        [
          174,
          202
        ],
        [
          245,
          205
        ],
        [
          255,
          191
        ],
        [
          257,
          188
        ]
      ],
      "category": "object"
    },
    "B1": {
      "id": "B1",
      "type": "blob",
      "polygon": [
        [
          279,
          195
        ],
        [
          340,
          0
        ],
        [
          371,
          36
        ],
        [
          394,
          146
        ],
        [
          397,
          188
        ],
        [
          363,
          202
        ],
        [
          306,
          203
        ],
        [
          279,
          202
        ],
        [
          280,
          199
        ]
      ],
      "category": "object"
    },
    "B10": {
      "id": "B10",
      "type": "blob",
      "polygon": [
        [
          203,
          671
        ],
        [
          161,
          784
        ],
        [
          165,
          677
        ],
        [
          137,
          677
        ],
        [
          142,
          779
        ],
        [
          90,
          664
        ],
        [
          81,
          687
        ],
        [
          92,
          731
        ],
        [
          118,
          772
        ],
        [
          128,
          802
        ],
        [
          134,
          825
        ],
        [
          146,
          836
        ],
        [
          161,
          835
        ],
        [
          171,
          799
        ],
        [
          188,
          769
        ],
        [
          202,
          725
        ],
        [
          218,
          691
        ],
        [
          222,
          673
        ],
        [
          195,
          670
        ],
        [
          201,
          670
        ]
      ],
      "category": "object"
    },
    "B11": {
      "id": "B11",
      "type": "blob",
      "polygon": [
        [
          255,
          1087
        ],
        [
          213,
          971
        ],
        [
          148,
          923
        ],
        [
          98,
          983
        ],
        [
          84,
          1041
        ],
        [
          95,
          1139
        ],
        [
          132,
          1206
        ],
        [
          142,
          1253
        ],
        [
          146,
          1279
        ],
        [
          178,
          1279
        ],
        [
          182,
          1206
        ],
        [
          205,
          1163
        ],
        [
          247,
          1104
        ],
        [
          252,
          1091
        ]
      ],
      "category": "object"
    },
    "B12": {
      "id": "B12",
      "type": "blob",
      "polygon": [
        [
          448,
          1042
        ],
        [
          513,
          1182
        ],
        [
          509,
          1269
        ],
        [
          549,
          1273
        ],
        [
          567,
          1271
        ],
        [
          573,
          1142
        ],
        [
          572,
          1099
        ],
        [
          587,
          1054
        ],
        [
          599,
          1030
        ],
        [
          538,
          1024
        ],
        [
          502,
          1025
        ],
        [
          449,
          1021
        ],
        [
          439,
          1030
        ],
        [
          444,
          1042
        ]
      ],
      "category": "object"
    },
    "B2": {
      "id": "B2",
      "type": "blob",
      "polygon": [
        [
          469,
          198
        ],
        [
          474,
          134
        ],
        [
          509,
          98
        ],
        [
          545,
          84
        ],
        [
          543,
          174
        ],
        [
          543,
          191
        ],
        [
          567,
          192
        ],
        [
          573,
          107
        ],
        [
          572,
          82
        ],
        [
          644,
          129
        ],
        [
          658,
          169
        ],
        [
          656,
          215
        ],
        [
          681,
          205
        ],
        [
          700,
          125
        ],
        [
          644,
          61
        ],
        [
          553,
          40
        ],
        [
          468,
          70
        ],
        [
          434,
          148
        ],
        [
          435,
          196
        ],
        [
          455,
          210
        ],
        [
          471,
          202
        ]
      ],
      "category": "object"
    },
    "B3": {
      "id": "B3",
      "type": "blob",
      "polygon": [
        [
          738,
          178
        ],
        [
          741,
          100
        ],
        [
          772,
          77
        ],
        [
          802,
          95
        ],
        [
          811,
          117
        ],
        [
          814,
          166
        ],
        [
          814,
          188
        ],
        [
          841,
          198
        ],
        [
          853,
          183
        ],
        [
          853,
          132
        ],
        [
          858,
          98
        ],
        [
          893,
          85
        ],
        [
          905,
          94
        ],
        [
          920,
          138
        ],
        [
          926,
          178
        ],
        [
          926,
          199
        ],
        [
          938,
          196
        ],
        [
          938,
          119
        ],
        [
          938,
          68
        ],
        [
          920,
          41
        ],
        [
          858,
          54
        ],
        [
          831,
          64
        ],
        [
          812,
          65
        ],
        [
          775,
          48
        ],
        [
          745,
          51
        ],
        [
          721,
          68
        ],
        [
          704,
          95
        ],
        [
          704,
          156
        ],
        [
          704,
          189
        ],
        [
          727,
          199
        ],
        [
          741,
          178
        ]
      ],
      "category": "object"
    },
    "B4": {
      "id": "B4",
      "type": "blob",
      "polygon": [
        [
          822,
          306
        ],
        [
          767,
          354
        ],
        [
          771,
          538
        ],
        [
          812,
          582
        ],
        [
          856,
          587
        ],
        [
          893,
          555
        ],
        [
          906,
          452
        ],
        [
          893,
          368
        ],
        [
          838,
          293
        ],
        [
          822,
          300
        ]
      ],
      "category": "object"
    },
    "B5": {
      "id": "B5",
      "type": "blob",
      "polygon": [
        [
          607,
          307
        ],
        [
          656,
          428
        ],
        [
          660,
          523
        ],
        [
          607,
          583
        ],
        [
          569,
          582
        ],
        [
          536,
          525
        ],
        [
          539,
          454
        ],
        [
          579,
          326
        ],
        [
          610,
          304
        ]
      ],
      "category": "object"
    },
    "B6": {
      "id": "B6",
      "type": "blob",
      "polygon": [
        [
          380,
          300
        ],
        [
          420,
          353
        ],
        [
          448,
          401
        ],
        [
          448,
          448
        ],
        [
          442,
          519
        ],
        [
          385,
          586
        ],
        [
          368,
          585
        ],
        [
          340,
          565
        ],
        [
          309,
          496
        ],
        [
          299,
          424
        ],
        [
          317,
          353
        ],
        [
          337,
          313
        ],
        [
          380,
          299
        ]
      ],
      "category": "object"
    },
    "B7": {
      "id": "B7",
      "type": "blob",
      "polygon": [
        [
          189,
          307
        ],
        [
          145,
          293
        ],
        [
          105,
          307
        ],
        [
          77,
          324
        ],
        [
          77,
          388
        ],
        [
          84,
          447
        ],
        [
          107,
          538
        ],
        [
          134,
          570
        ],
        [
          154,
          582
        ],
        [
          186,
          518
        ],
        [
          218,
          445
        ],
        [
          218,
          384
        ],
        [
          220,
          353
        ],
        [
          193,
          307
        ]
      ],
      "category": "object"
    },
    "B8": {
      "id": "B8",
      "type": "blob",
      "polygon": [
        [
          546,
          667
        ],
        [
          530,
          724
        ],
        [
          499,
          765
        ],
        [
          461,
          782
        ],
        [
          445,
          788
        ],
        [
          441,
          667
        ],
        [
          420,
          670
        ],
        [
          422,
          784
        ],
        [
          371,
          774
        ],
        [
          336,
          728
        ],
        [
          323,
          684
        ],
        [
          310,
          674
        ],
        [
          292,
          680
        ],
        [
          314,
          732
        ],
        [
          341,
          767
        ],
        [
          385,
          796
        ],
        [
          411,
          802
        ],
        [
          422,
          819
        ],
        [
          438,
          822
        ],
        [
          449,
          808
        ],
        [
          484,
          804
        ],
        [
          518,
          791
        ],
        [
          553,
          755
        ],
        [
          570,
          707
        ],
        [
          569,
          681
        ],
        [
          550,
          667
        ]
      ],
      "category": "object"
    },
    "B9": {
      "id": "B9",
      "type": "blob",
      "polygon": [
        [
          647,
          687
        ],
        [
          713,
          734
        ],
        [
          744,
          779
        ],
        [
          751,
          819
        ],
        [
          782,
          821
        ],
        [
          786,
          788
        ],
        [
          818,
          748
        ],
        [
          866,
          715
        ],
        [
          890,
          676
        ],
        [
          879,
          674
        ],
        [
          848,
          690
        ],
        [
          808,
          718
        ],
        [
          784,
          758
        ],
        [
          774,
          765
        ],
        [
          779,
          691
        ],
        [
          764,
          668
        ],
        [
          755,
          684
        ],
        [
          754,
          724
        ],
        [
          754,
          755
        ],
        [
          731,
          724
        ],
        [
          693,
          686
        ],
        [
          674,
          676
        ],
        [
          653,
          676
        ],
        [
          649,
          688
        ]
      ],
      "category": "object"
    },
    "A0": {
      "id": "A0",
      "type": "arrow",
      "polygon": [
        [
          543,
          1180
        ],
        [
          684,
          1095
        ],
        [
          676,
          1078
        ],
        [
          525,
          1161
        ],
        [
          539,
          1176
        ]
      ],
      "category": "connector"
    },
    "A1": {
      "id": "A1",
      "type": "arrow",
      "polygon": [
        [
          402,
          1112
        ],
        [
          508,
          1071
        ],
        [
          499,
          1057
        ],
        [
          397,
          1091
        ],
        [
          402,
          1114
        ]
      ],
      "category": "connector"
    },
    "A2": {
      "id": "A2",
      "type": "arrow",
      "polygon": [
        [
          397,
          1207
        ],
        [
          539,
          1242
        ],
        [
          542,
          1230
        ],
        [
          404,
          1192
        ],
        [
          397,
          1203
        ]
      ],
      "category": "connector"
    },
    "A3": {
      "id": "A3",
      "type": "arrow",
      "polygon": [
        [
          166,
          1269
        ],
        [
          296,
          1212
        ],
        [
          290,
          1190
        ],
        [
          162,
          1246
        ],
        [
          164,
          1270
        ]
      ],
      "category": "connector"
    },
    "A4": {
      "id": "A4",
      "type": "arrow",
      "polygon": [
        [
          202,
          1067
        ],
        [
          290,
          1106
        ],
        [
          302,
          1102
        ],
        [
          215,
          1048
        ],
        [
          203,
          1064
        ]
      ],
      "category": "connector"
    }
  },
  "relationships": [
    {
      "id": "T0+B0",
      "type": "intraObjectLabel",
      "source": "T0",
      "target": "B0",
      "connector": null,
      "directional": false
    },
    {
      "id": "T1+B1",
      "type": "intraObjectLabel",
      "source": "T1",
      "target": "B1",
      "connector": null,
      "directional": false
    },
    {
      "id": "T10+B9",
      "type": "intraObjectLabel",
      "source": "T10",
      "target": "B9",
      "connector": null,
      "directional": false
    },
    {
      "id": "T11+A0+B12",
      "type": "intraObjectLinkage",
      "source": "T11",
      "target": "B12",
      "connector": "A0",
      "directional": false
    },
    {
      "id": "T12+A1+B12",
      "type": "intraObjectLinkage",
      "source": "T12",
      "target": "B12",
      "connector": "A1",
      "directional": false
    },
    {
      "id": "T13+A2+B12",
      "type": "intraObjectLinkage",
      "source": "T13",
      "target": "B12",
      "connector": "A2",
      "directional": false
    },
    {
      "id": "T14+I0",
      "type": "sectionTitle",
      "source": "T14",
      "target": "I0",
      "connector": null,
      "directional": false
    },
    {
      "id": "T15+I0",
      "type": "sectionTitle",
      "source": "T15",
      "target": "I0",
      "connector": null,
      "directional": false
    },
    {
      "id": "T16+I0",
      "type": "sectionTitle",
      "source": "T16",
      "target": "I0",
      "connector": null,
      "directional": false
    },
    {
      "id": "T17+I0",
      "type": "sectionTitle",
      "source": "T17",
      "target": "I0",
      "connector": null,
      "directional": false
    },
    {
      "id": "T2+B2",
      "type": "intraObjectLabel",
      "source": "T2",
      "target": "B2",
      "connector": null,
      "directional": false
    },
    {
      "id": "T3+B3",
      "type": "intraObjectLabel",
      "source": "T3",
      "target": "B3",
      "connector": null,
      "directional": false
    },
    {
      "id": "T4+B4",
      "type": "intraObjectLabel",
      "source": "T4",
      "target": "B4",
      "connector": null,
      "directional": false
    },
    {
      "id": "T5+B5",
      "type": "intraObjectLabel",
      "source": "T5",
      "target": "B5",
      "connector": null,
      "directional": false
    },
    {
      "id": "T6+B6",
      "type": "intraObjectLabel",
      "source": "T6",
      "target": "B6",
      "connector": null,
      "directional": false
    },
    {
      "id": "T7+B7",
      "type": "intraObjectLabel",
      "source": "T7",
      "target": "B7",
      "connector": null,
      "directional": false
    },
    {
      "id": "T8+B10",
      "type": "intraObjectLabel",
      "source": "T8",
      "target": "B10",
      "connector": null,
      "directional": false
    },
    {
      "id": "T9+B8",
      "type": "intraObjectLabel",
      "source": "T9",
      "target": "B8",
      "connector": null,
      "directional": false
    }
  ],
  "semantic_roles": {
    "T0": "part_label",
    "T1": "part_label",
    "T10": "part_label",
    "T11": "part_label",
    "T12": "part_label",
    "T13": "part_label",
    "T14": "part_label",
    "T15": "part_label",
    "T16": "part_label",
    "T17": "part_label",
    "T2": "part_label",
    "T3": "part_label",
    "T4": "part_label",
    "T5": "part_label",
    "T6": "part_label",
    "T7": "part_label",
    "T8": "part_label",
    "T9": "part_label",
    "B0": "whole",
    "B1": "whole",
    "B10": "whole",
    "B11": "whole",
    "B12": "whole",
    "B2": "whole",
    "B3": "whole",
    "B4": "whole",
    "B5": "whole",
    "B6": "whole",
    "B7": "whole",
    "B8": "whole",
    "B9": "whole",
    "A0": "connector",
    "A1": "connector",
    "A2": "connector",
    "A3": "connector",
    "A4": "connector"
  },
  "educational_context": {
    "subject": "unknown",
    "diagram_type": "labeled_illustration",
    "text_content": "acuminate straight convex landmark lamina petiole d c b a rounded emarginate oblong ovate elliptic obovate straight rounded"
  },
  "questions": [
    {
      "question_text": "What is between the lamina and petiole in D?",
      "question_id": "4733.png-0",
      "answers": [
        "landmark",
        "shift",
        "none of the above",
        "crust"
      ],
      "correct_answer_index": 0,
      "abc_label": false
    },
    {
      "question_text": "Which of these is not represented in the figure?",
      "question_id": "4733.png-1",
      "answers": [
        "none of the above",
        "ovate",
        "triangular",
        "convex"
      ],
      "correct_answer_index": 2,
      "abc_label": false
    }
  ]
}